<?xml version="1.0" encoding="UTF-8" ?>
<!DOCTYPE mapper PUBLIC "-//mybatis.org//DTD Mapper 3.0//EN" "http://mybatis.org/dtd/mybatis-3-mapper.dtd" >
<mapper namespace="com.tiger.framework.dao.ProductMapper" >
  <resultMap id="BaseResultMap" type="com.tiger.framework.datamodel.Product" >
    <!--
      WARNING - @mbggenerated
      This element is automatically generated by MyBatis Generator, do not modify.
      This element was generated on Tue May 31 17:27:56 CST 2016.
    -->
    <id column="id" property="id" jdbcType="BIGINT" />
    <result column="name" property="name" jdbcType="VARCHAR" />
    <result column="description" property="description" jdbcType="VARCHAR" />
    <result column="parent_category_id" property="parentCategoryId" jdbcType="BIGINT" />
    <result column="on_shelf" property="onShelf" jdbcType="TINYINT"/>
  </resultMap>
  <resultMap id="ResultMapWithBLOBs" type="com.tiger.framework.datamodel.Product" extends="BaseResultMap" >
    <!--
      WARNING - @mbggenerated
      This element is automatically generated by MyBatis Generator, do not modify.
      This element was generated on Tue May 31 17:27:56 CST 2016.
    -->
    <result column="long_description" property="longDescription" jdbcType="LONGVARCHAR" />
  </resultMap>
  <sql id="Base_Column_List" >
    <!--
      WARNING - @mbggenerated
      This element is automatically generated by MyBatis Generator, do not modify.
      This element was generated on Tue May 31 17:27:56 CST 2016.
    -->
    id, name, description, parent_category_id, on_shelf
  </sql>
  <sql id="Blob_Column_List" >
    <!--
      WARNING - @mbggenerated
      This element is automatically generated by MyBatis Generator, do not modify.
      This element was generated on Tue May 31 17:27:56 CST 2016.
    -->
    long_description
  </sql>

  <select id="listProducts" resultMap="ResultMapWithBLOBs" parameterType="PageBounds">
    select
    <include refid="Base_Column_List" />
    ,
    <include refid="Blob_Column_List" />
    from product
    <if test="q != null and q != '' ">
       WHERE name like  CONCAT('%',#{q,jdbcType=VARCHAR},'%') or
      description like CONCAT('%',#{q,jdbcType=VARCHAR},'%') or
      long_description like CONCAT('%',#{q,jdbcType=VARCHAR},'%')
    </if>
  </select>

  <select id="selectByPrimaryKey" resultMap="ResultMapWithBLOBs" parameterType="java.lang.Long" >
    <!--
      WARNING - @mbggenerated
      This element is automatically generated by MyBatis Generator, do not modify.
      This element was generated on Tue May 31 17:27:56 CST 2016.
    -->
    select 
    <include refid="Base_Column_List" />
    ,
    <include refid="Blob_Column_List" />
    from product
    where id = #{id,jdbcType=BIGINT}
  </select>
  <delete id="deleteByPrimaryKey" parameterType="java.lang.Long" >
    <!--
      WARNING - @mbggenerated
      This element is automatically generated by MyBatis Generator, do not modify.
      This element was generated on Tue May 31 17:27:56 CST 2016.
    -->
    delete from product
    where id = #{id,jdbcType=BIGINT}
  </delete>
  <insert id="insert" parameterType="com.tiger.framework.datamodel.Product" >
    <!--
      WARNING - @mbggenerated
      This element is automatically generated by MyBatis Generator, do not modify.
      This element was generated on Tue May 31 17:27:56 CST 2016.
    -->
    insert into product (id, name, description, 
      parent_category_id, long_description)
    values (#{id,jdbcType=BIGINT}, #{name,jdbcType=VARCHAR}, #{description,jdbcType=VARCHAR}, 
      #{parentCategoryId,jdbcType=BIGINT}, #{longDescription,jdbcType=LONGVARCHAR})
  </insert>
  <insert id="insertSelective" parameterType="com.tiger.framework.datamodel.Product" >
    <!--
      WARNING - @mbggenerated
      This element is automatically generated by MyBatis Generator, do not modify.
      This element was generated on Tue May 31 17:27:56 CST 2016.
    -->
    insert into product
    <trim prefix="(" suffix=")" suffixOverrides="," >
      <if test="id != null" >
        id,
      </if>
      <if test="name != null" >
        name,
      </if>
      <if test="description != null" >
        description,
      </if>
      <if test="parentCategoryId != null" >
        parent_category_id,
      </if>
      <if test="longDescription != null" >
        long_description,
      </if>
    </trim>
    <trim prefix="values (" suffix=")" suffixOverrides="," >
      <if test="id != null" >
        #{id,jdbcType=BIGINT},
      </if>
      <if test="name != null" >
        #{name,jdbcType=VARCHAR},
      </if>
      <if test="description != null" >
        #{description,jdbcType=VARCHAR},
      </if>
      <if test="parentCategoryId != null" >
        #{parentCategoryId,jdbcType=BIGINT},
      </if>
      <if test="longDescription != null" >
        #{longDescription,jdbcType=LONGVARCHAR},
      </if>
    </trim>
  </insert>
  <update id="updateByPrimaryKeySelective" parameterType="com.tiger.framework.datamodel.Product" >
    <!--
      WARNING - @mbggenerated
      This element is automatically generated by MyBatis Generator, do not modify.
      This element was generated on Tue May 31 17:27:56 CST 2016.
    -->
    update product
    <set >
      <if test="name != null" >
        name = #{name,jdbcType=VARCHAR},
      </if>
      <if test="description != null" >
        description = #{description,jdbcType=VARCHAR},
      </if>
      <if test="parentCategoryId != null" >
        parent_category_id = #{parentCategoryId,jdbcType=BIGINT},
      </if>
      <if test="longDescription != null" >
        long_description = #{longDescription,jdbcType=LONGVARCHAR},
      </if>
      <if test="onShelf !=null " >
        on_shelf = #{onShelf,jdbcType=TINYINT}
      </if>

    </set>
    where id = #{id,jdbcType=BIGINT}
  </update>
  <update id="updateByPrimaryKeyWithBLOBs" parameterType="com.tiger.framework.datamodel.Product" >
    <!--
      WARNING - @mbggenerated
      This element is automatically generated by MyBatis Generator, do not modify.
      This element was generated on Tue May 31 17:27:56 CST 2016.
    -->
    update product
    set name = #{name,jdbcType=VARCHAR},
      description = #{description,jdbcType=VARCHAR},
      parent_category_id = #{parentCategoryId,jdbcType=BIGINT},
      long_description = #{longDescription,jdbcType=LONGVARCHAR}
    where id = #{id,jdbcType=BIGINT}
  </update>
  <update id="updateByPrimaryKey" parameterType="com.tiger.framework.datamodel.Product" >
    <!--
      WARNING - @mbggenerated
      This element is automatically generated by MyBatis Generator, do not modify.
      This element was generated on Tue May 31 17:27:56 CST 2016.
    -->
    update product
    set name = #{name,jdbcType=VARCHAR},
      description = #{description,jdbcType=VARCHAR},
      parent_category_id = #{parentCategoryId,jdbcType=BIGINT}
    where id = #{id,jdbcType=BIGINT}
  </update>
  
  <resultMap id="skuListDTO" type="com.tiger.framework.dto.SkuListDTO">
	<id column="ID" jdbcType="BIGINT" property="id" />
	<result column="PRODUCTID" jdbcType="BIGINT" property="productId" />
	<result column="NAME" jdbcType="VARCHAR" property="name" />
	<result column="PRICE" jdbcType="BIGINT" property="price" />
	<result column="IMG" jdbcType="VARCHAR" property="img" />
	<result column="stock_level" jdbcType="BIGINT" property="stockLevel" />
  </resultMap>
  <select id="selectSkuListDTO" resultMap="skuListDTO">
  	select s.id as id,p.id as productid, s.name,s.sale_price as price,
  	s.stock_level as stockLevel
  	from sku s left join product p on s.product_id = p.id
  	where 1=1 
  	<if test="productId != null" >
  		and p.id = #{productId}
  	</if>
  </select>
</mapper>